{
  "releases": {
    "1.9": {
      "name": "1.9",
      "releaseDate": "2023-01-24",
      "eol": "2023-08-01",
      "minK8sVersion": "1.24"
    },
    "1.8": {
      "name": "1.8",
      "releaseDate": "2022-10-18",
      "eol": "2023-05-02",
      "minK8sVersion": "1.23"
    },
    "1.7": {
      "name": "1.7",
      "releaseDate": "2022-08-23",
      "eol": "2023-02-21",
      "minK8sVersion": "1.22"
    },
    "1.6": {
      "name": "1.6",
      "releaseDate": "2022-07-12",
      "eol": "2023-01-10",
      "minK8sVersion": "1.22"
    },
    "1.5": {
      "name": "1.5",
      "releaseDate": "2022-05-31",
      "eol": "2022-11-29",
      "minK8sVersion": "1.22"
    },
    "1.4": {
      "name": "1.4",
      "releaseDate": "2022-04-19",
      "eol": "2022-10-11",
      "minK8sVersion": "1.22"
    },
    "1.3": {
      "name": "1.3",
      "releaseDate": "2022-03-08",
      "eol": "2022-08-30",
      "minK8sVersion": "1.21"
    },
    "1.21": {
      "name": "1.21",
      "releaseDate": "2026-01-27",
      "eol": "2026-08-04",
      "minK8sVersion": "1.33"
    },
    "1.20": {
      "name": "1.20",
      "releaseDate": "2025-10-21",
      "eol": "2026-05-05",
      "minK8sVersion": "1.32"
    },
    "1.2": {
      "name": "1.2",
      "releaseDate": "2022-01-25",
      "eol": "2022-07-12",
      "minK8sVersion": "1.21"
    },
    "1.19": {
      "name": "1.19",
      "releaseDate": "2025-07-22",
      "eol": "2026-02-03",
      "minK8sVersion": "1.32"
    },
    "1.18": {
      "name": "1.18",
      "releaseDate": "2025-04-22",
      "eol": "2025-10-28",
      "minK8sVersion": "1.31"
    },
    "1.17": {
      "name": "1.17",
      "releaseDate": "2025-01-28",
      "eol": "2025-07-28",
      "minK8sVersion": "1.30"
    },
    "1.16": {
      "name": "1.16",
      "releaseDate": "2024-10-22",
      "eol": "2025-04-22",
      "minK8sVersion": "1.29"
    },
    "1.15": {
      "name": "1.15",
      "releaseDate": "2024-07-23",
      "eol": "2025-01-21",
      "minK8sVersion": "1.28"
    },
    "1.14": {
      "name": "1.14",
      "releaseDate": "2024-04-23",
      "eol": "2024-10-22",
      "minK8sVersion": "1.28"
    },
    "1.13": {
      "name": "1.13",
      "releaseDate": "2024-01-23",
      "eol": "2024-07-22",
      "minK8sVersion": "1.27"
    },
    "1.12": {
      "name": "1.12",
      "releaseDate": "2023-10-24",
      "eol": "2024-04-30",
      "minK8sVersion": "1.26"
    },
    "1.11": {
      "name": "1.11",
      "releaseDate": "2023-07-25",
      "eol": "2024-01-30",
      "minK8sVersion": "1.25"
    },
    "1.10": {
      "name": "1.10",
      "releaseDate": "2023-04-25",
      "eol": "2023-10-31",
      "minK8sVersion": "1.24"
    },
    "1.1": {
      "name": "1.1",
      "releaseDate": "2021-12-14",
      "eol": "2022-05-31",
      "minK8sVersion": "1.20"
    },
    "1.0": {
      "name": "1.0",
      "releaseDate": "2021-11-02",
      "eol": "2022-04-19",
      "minK8sVersion": "1.20"
    },
    "0.26": {
      "name": "0.26",
      "releaseDate": "2021-09-21",
      "eol": "2022-03-08",
      "minK8sVersion": "1.19"
    },
    "0.25": {
      "name": "0.25",
      "releaseDate": "2021-08-10",
      "eol": "2022-01-25",
      "minK8sVersion": "1.19"
    },
    "0.24": {
      "name": "0.24",
      "releaseDate": "2021-06-29",
      "eol": "2021-12-14",
      "minK8sVersion": "1.19"
    },
    "0.23": {
      "name": "0.23",
      "releaseDate": "2021-05-18",
      "eol": "2021-11-02",
      "minK8sVersion": "1.18"
    },
    "0.22": {
      "name": "0.22",
      "releaseDate": "2021-04-06",
      "eol": "2021-09-21",
      "minK8sVersion": "1.18"
    },
    "0.21": {
      "name": "0.21",
      "releaseDate": "2021-02-23",
      "eol": "2021-08-10",
      "minK8sVersion": "1.18"
    },
    "0.20": {
      "name": "0.20",
      "releaseDate": "2021-01-12",
      "eol": "2021-06-29",
      "minK8sVersion": "1.17"
    },
    "0.19": {
      "name": "0.19",
      "releaseDate": "2020-11-10",
      "eol": "2021-05-18",
      "minK8sVersion": "1.17"
    },
    "0.18": {
      "name": "0.18",
      "releaseDate": "2020-09-29",
      "eol": "2021-03-16",
      "minK8sVersion": "1.17"
    },
    "0.17": {
      "name": "0.17",
      "releaseDate": "2020-08-18",
      "eol": "2021-02-02",
      "minK8sVersion": "1.16"
    },
    "0.16": {
      "name": "0.16",
      "releaseDate": "2020-07-07",
      "eol": "2020-12-22",
      "minK8sVersion": "1.16"
    },
    "0.15": {
      "name": "0.15",
      "releaseDate": "2020-05-26",
      "eol": "2020-11-10",
      "minK8sVersion": "1.16"
    },
    "0.14": {
      "name": "0.14",
      "releaseDate": "2020-04-14",
      "eol": "2020-09-29",
      "minK8sVersion": "1.15"
    },
    "0.13": {
      "name": "0.13",
      "releaseDate": "2020-03-03",
      "eol": "2020-08-18",
      "minK8sVersion": "1.15"
    }
  },
  "versions": {
    "1.21.1": {
      "name": "1.21.1",
      "date": "2026-02-24"
    },
    "1.20.3": {
      "name": "1.20.3",
      "date": "2026-02-24"
    },
    "1.19.9": {
      "name": "1.19.9",
      "date": "2026-01-28"
    },
    "1.21.0": {
      "name": "1.21.0",
      "date": "2026-01-27"
    },
    "1.20.2": {
      "name": "1.20.2",
      "date": "2026-01-27"
    },
    "1.20.1": {
      "name": "1.20.1",
      "date": "2025-12-25"
    },
    "1.19.8": {
      "name": "1.19.8",
      "date": "2025-12-23"
    },
    "1.20.0": {
      "name": "1.20.0",
      "date": "2025-10-29"
    },
    "1.19.7": {
      "name": "1.19.7",
      "date": "2025-10-24"
    },
    "1.18.2": {
      "name": "1.18.2",
      "date": "2025-10-24"
    },
    "1.19.6": {
      "name": "1.19.6",
      "date": "2025-09-16"
    },
    "1.19.5": {
      "name": "1.19.5",
      "date": "2025-09-09"
    },
    "1.19.4": {
      "name": "1.19.4",
      "date": "2025-09-02"
    },
    "1.19.3": {
      "name": "1.19.3",
      "date": "2025-09-02"
    },
    "1.19.2": {
      "name": "1.19.2",
      "date": "2025-08-26"
    },
    "1.19.1": {
      "name": "1.19.1",
      "date": "2025-08-19"
    },
    "1.19.0": {
      "name": "1.19.0",
      "date": "2025-07-22"
    },
    "1.18.1": {
      "name": "1.18.1",
      "date": "2025-06-10"
    },
    "1.17.2": {
      "name": "1.17.2",
      "date": "2025-06-10"
    },
    "1.17.1": {
      "name": "1.17.1",
      "date": "2025-05-02"
    },
    "1.18.0": {
      "name": "1.18.0",
      "date": "2025-04-22"
    },
    "1.16.3": {
      "name": "1.16.3",
      "date": "2025-03-11"
    },
    "1.16.2": {
      "name": "1.16.2",
      "date": "2025-01-28"
    },
    "1.17.0": {
      "name": "1.17.0",
      "date": "2025-01-22"
    },
    "1.15.3": {
      "name": "1.15.3",
      "date": "2025-01-22"
    },
    "1.16.1": {
      "name": "1.16.1",
      "date": "2025-01-21"
    },
    "1.16.0": {
      "name": "1.16.0",
      "date": "2024-10-22"
    },
    "1.14.2": {
      "name": "1.14.2",
      "date": "2024-10-08"
    },
    "1.15.2": {
      "name": "1.15.2",
      "date": "2024-08-06"
    },
    "1.15.1": {
      "name": "1.15.1",
      "date": "2024-08-01"
    },
    "1.15.0": {
      "name": "1.15.0",
      "date": "2024-07-23"
    },
    "1.14.1": {
      "name": "1.14.1",
      "date": "2024-05-28"
    },
    "1.13.2": {
      "name": "1.13.2",
      "date": "2024-05-28"
    },
    "1.14.0": {
      "name": "1.14.0",
      "date": "2024-04-23"
    },
    "1.13.1": {
      "name": "1.13.1",
      "date": "2024-02-03"
    },
    "1.12.4": {
      "name": "1.12.4",
      "date": "2024-02-02"
    },
    "1.13.0": {
      "name": "1.13.0",
      "date": "2024-01-24"
    },
    "1.12.3": {
      "name": "1.12.3",
      "date": "2023-12-19"
    },
    "1.11.6": {
      "name": "1.11.6",
      "date": "2023-12-19"
    },
    "1.12.2": {
      "name": "1.12.2",
      "date": "2023-11-28"
    },
    "1.11.5": {
      "name": "1.11.5",
      "date": "2023-11-28"
    },
    "1.12.1": {
      "name": "1.12.1",
      "date": "2023-11-21"
    },
    "1.11.4": {
      "name": "1.11.4",
      "date": "2023-11-03"
    },
    "1.10.6": {
      "name": "1.10.6",
      "date": "2023-11-01"
    },
    "1.10.5": {
      "name": "1.10.5",
      "date": "2023-10-31"
    },
    "1.12.0": {
      "name": "1.12.0",
      "date": "2023-10-24"
    },
    "1.11.3": {
      "name": "1.11.3",
      "date": "2023-10-24"
    },
    "1.11.2": {
      "name": "1.11.2",
      "date": "2023-10-17"
    },
    "1.10.4": {
      "name": "1.10.4",
      "date": "2023-10-17"
    },
    "1.11.1": {
      "name": "1.11.1",
      "date": "2023-09-19"
    },
    "1.10.3": {
      "name": "1.10.3",
      "date": "2023-09-19"
    },
    "1.11.0": {
      "name": "1.11.0",
      "date": "2023-07-25"
    },
    "1.9.4": {
      "name": "1.9.4",
      "date": "2023-06-06"
    },
    "1.10.2": {
      "name": "1.10.2",
      "date": "2023-06-06"
    },
    "1.10.1": {
      "name": "1.10.1",
      "date": "2023-05-09"
    },
    "1.10.0": {
      "name": "1.10.0",
      "date": "2023-04-25"
    },
    "1.9.3": {
      "name": "1.9.3",
      "date": "2023-04-04"
    },
    "1.8.6": {
      "name": "1.8.6",
      "date": "2023-04-04"
    },
    "1.9.2": {
      "name": "1.9.2",
      "date": "2023-02-28"
    },
    "1.8.5": {
      "name": "1.8.5",
      "date": "2023-02-28"
    },
    "1.9.1": {
      "name": "1.9.1",
      "date": "2023-02-27"
    },
    "1.8.4": {
      "name": "1.8.4",
      "date": "2023-02-27"
    },
    "1.9.0": {
      "name": "1.9.0",
      "date": "2023-01-25"
    },
    "1.8.3": {
      "name": "1.8.3",
      "date": "2022-12-08"
    },
    "1.7.4": {
      "name": "1.7.4",
      "date": "2022-12-08"
    },
    "1.6.3": {
      "name": "1.6.3",
      "date": "2022-12-08"
    },
    "1.8.2": {
      "name": "1.8.2",
      "date": "2022-12-06"
    },
    "1.8.1": {
      "name": "1.8.1",
      "date": "2022-11-29"
    },
    "1.7.3": {
      "name": "1.7.3",
      "date": "2022-11-29"
    },
    "1.6.2": {
      "name": "1.6.2",
      "date": "2022-11-29"
    },
    "1.5.1": {
      "name": "1.5.1",
      "date": "2022-11-29"
    },
    "1.8.0": {
      "name": "1.8.0",
      "date": "2022-10-19"
    },
    "1.7.2": {
      "name": "1.7.2",
      "date": "2022-09-27"
    },
    "1.6.1": {
      "name": "1.6.1",
      "date": "2022-09-27"
    },
    "1.7.1": {
      "name": "1.7.1",
      "date": "2022-08-24"
    },
    "1.7.0": {
      "name": "1.7.0",
      "date": "2022-08-23"
    },
    "1.6.0": {
      "name": "1.6.0",
      "date": "2022-07-12"
    },
    "1.5.0": {
      "name": "1.5.0",
      "date": "2022-05-31"
    },
    "1.4.0": {
      "name": "1.4.0",
      "date": "2022-04-19"
    },
    "1.3.2": {
      "name": "1.3.2",
      "date": "2022-04-14"
    },
    "1.2.5": {
      "name": "1.2.5",
      "date": "2022-04-14"
    },
    "1.3.1": {
      "name": "1.3.1",
      "date": "2022-04-08"
    },
    "1.2.4": {
      "name": "1.2.4",
      "date": "2022-04-08"
    },
    "1.3.0": {
      "name": "1.3.0",
      "date": "2022-03-08"
    },
    "1.2.3": {
      "name": "1.2.3",
      "date": "2022-03-01"
    },
    "1.1.4": {
      "name": "1.1.4",
      "date": "2022-02-25"
    },
    "1.0.2": {
      "name": "1.0.2",
      "date": "2022-02-24"
    },
    "1.2.2": {
      "name": "1.2.2",
      "date": "2022-02-17"
    },
    "1.1.3": {
      "name": "1.1.3",
      "date": "2022-02-15"
    },
    "1.2.1": {
      "name": "1.2.1",
      "date": "2022-02-14"
    },
    "1.2.0": {
      "name": "1.2.0",
      "date": "2022-01-25"
    },
    "1.1.2": {
      "name": "1.1.2",
      "date": "2022-01-25"
    },
    "1.1.1": {
      "name": "1.1.1",
      "date": "2022-01-18"
    },
    "1.1.0": {
      "name": "1.1.0",
      "date": "2021-12-14"
    },
    "1.0.1": {
      "name": "1.0.1",
      "date": "2021-11-16"
    },
    "1.0.0": {
      "name": "1.0.0",
      "date": "2021-11-02"
    }
  }
}