{
  "releases": {},
  "versions": {
    "1.6.36": {
      "name": "1.6.36",
      "date": "2025-02-04"
    },
    "1.6.35": {
      "name": "1.6.35",
      "date": "2025-02-01"
    },
    "1.6.34": {
      "name": "1.6.34",
      "date": "2024-12-22"
    },
    "1.6.33": {
      "name": "1.6.33",
      "date": "2024-12-04"
    },
    "1.6.32": {
      "name": "1.6.32",
      "date": "2024-10-20"
    },
    "1.6.31": {
      "name": "1.6.31",
      "date": "2024-09-07"
    },
    "1.6.30": {
      "name": "1.6.30",
      "date": "2024-09-05"
    },
    "1.6.29": {
      "name": "1.6.29",
      "date": "2024-06-28"
    },
    "1.6.28": {
      "name": "1.6.28",
      "date": "2024-05-31"
    },
    "1.6.27": {
      "name": "1.6.27",
      "date": "2024-05-05"
    },
    "1.6.26": {
      "name": "1.6.26",
      "date": "2024-03-27"
    },
    "1.6.25": {
      "name": "1.6.25",
      "date": "2024-03-19"
    },
    "1.6.24": {
      "name": "1.6.24",
      "date": "2024-02-27"
    },
    "1.6.23": {
      "name": "1.6.23",
      "date": "2024-01-09"
    },
    "1.6.22": {
      "name": "1.6.22",
      "date": "2023-10-15"
    },
    "1.6.21": {
      "name": "1.6.21",
      "date": "2023-06-15"
    },
    "1.6.20": {
      "name": "1.6.20",
      "date": "2023-05-12"
    },
    "1.6.19": {
      "name": "1.6.19",
      "date": "2023-03-08"
    },
    "1.6.18": {
      "name": "1.6.18",
      "date": "2023-01-10"
    },
    "1.6.17": {
      "name": "1.6.17",
      "date": "2022-08-26"
    },
    "1.6.16": {
      "name": "1.6.16",
      "date": "2022-08-03"
    },
    "1.6.15": {
      "name": "1.6.15",
      "date": "2022-03-29"
    },
    "1.6.14": {
      "name": "1.6.14",
      "date": "2022-02-09"
    },
    "1.6.13": {
      "name": "1.6.13",
      "date": "2022-01-12"
    },
    "1.6.12": {
      "name": "1.6.12",
      "date": "2021-09-28"
    },
    "1.6.11": {
      "name": "1.6.11",
      "date": "2021-09-27"
    },
    "1.6.10": {
      "name": "1.6.10",
      "date": "2021-07-25"
    },
    "1.6.9": {
      "name": "1.6.9",
      "date": "2020-11-20"
    },
    "1.6.8": {
      "name": "1.6.8",
      "date": "2020-10-26"
    },
    "1.6.7": {
      "name": "1.6.7",
      "date": "2020-09-04"
    },
    "1.6.6": {
      "name": "1.6.6",
      "date": "2020-05-12"
    },
    "1.6.5": {
      "name": "1.6.5",
      "date": "2020-04-13"
    },
    "1.6.4": {
      "name": "1.6.4",
      "date": "2020-04-12"
    },
    "1.6.3": {
      "name": "1.6.3",
      "date": "2020-03-28"
    },
    "1.6.2": {
      "name": "1.6.2",
      "date": "2020-03-23"
    },
    "1.6.1": {
      "name": "1.6.1",
      "date": "2020-03-16"
    },
    "1.6.0": {
      "name": "1.6.0",
      "date": "2020-03-08"
    },
    "1.5.22": {
      "name": "1.5.22",
      "date": "2020-02-01"
    },
    "1.5.21": {
      "name": "1.5.21",
      "date": "2020-01-21"
    },
    "1.5.20": {
      "name": "1.5.20",
      "date": "2019-11-11"
    },
    "1.5.19": {
      "name": "1.5.19",
      "date": "2019-09-30"
    },
    "1.5.18": {
      "name": "1.5.18",
      "date": "2019-09-17"
    },
    "1.5.17": {
      "name": "1.5.17",
      "date": "2019-08-29"
    },
    "1.5.16": {
      "name": "1.5.16",
      "date": "2019-05-24"
    },
    "1.5.15": {
      "name": "1.5.15",
      "date": "2019-05-20"
    },
    "1.5.14": {
      "name": "1.5.14",
      "date": "2019-04-27"
    },
    "1.5.13": {
      "name": "1.5.13",
      "date": "2019-04-15"
    },
    "1.5.12": {
      "name": "1.5.12",
      "date": "2018-11-03"
    },
    "1.5.11": {
      "name": "1.5.11",
      "date": "2018-10-10"
    },
    "1.5.10": {
      "name": "1.5.10",
      "date": "2018-08-10"
    },
    "1.5.9": {
      "name": "1.5.9",
      "date": "2018-07-07"
    },
    "1.5.8": {
      "name": "1.5.8",
      "date": "2018-05-25"
    },
    "1.5.7": {
      "name": "1.5.7",
      "date": "2018-03-28"
    },
    "1.5.6": {
      "name": "1.5.6",
      "date": "2018-02-27"
    },
    "1.5.5": {
      "name": "1.5.5",
      "date": "2018-02-12"
    },
    "1.5.4": {
      "name": "1.5.4",
      "date": "2017-12-20"
    },
    "1.5.3": {
      "name": "1.5.3",
      "date": "2017-11-04"
    },
    "1.5.2": {
      "name": "1.5.2",
      "date": "2017-09-30"
    },
    "1.5.1": {
      "name": "1.5.1",
      "date": "2017-08-24"
    },
    "1.5.0": {
      "name": "1.5.0",
      "date": "2017-07-21"
    },
    "1.4.39": {
      "name": "1.4.39",
      "date": "2017-07-04"
    },
    "1.4.38": {
      "name": "1.4.38",
      "date": "2017-06-24"
    },
    "1.4.37": {
      "name": "1.4.37",
      "date": "2017-06-04"
    },
    "1.4.36": {
      "name": "1.4.36",
      "date": "2017-03-19"
    },
    "1.4.35": {
      "name": "1.4.35",
      "date": "2017-02-26"
    },
    "1.4.34": {
      "name": "1.4.34",
      "date": "2017-01-07"
    },
    "1.4.33": {
      "name": "1.4.33",
      "date": "2016-10-31"
    },
    "1.4.32": {
      "name": "1.4.32",
      "date": "2016-10-12"
    },
    "1.4.31": {
      "name": "1.4.31",
      "date": "2016-08-19"
    },
    "1.4.30": {
      "name": "1.4.30",
      "date": "2016-08-11"
    },
    "1.4.29": {
      "name": "1.4.29",
      "date": "2016-07-13"
    },
    "1.4.28": {
      "name": "1.4.28",
      "date": "2016-07-01"
    },
    "1.4.27": {
      "name": "1.4.27",
      "date": "2016-06-24"
    },
    "1.4.26": {
      "name": "1.4.26",
      "date": "2016-06-17"
    },
    "1.4.25": {
      "name": "1.4.25",
      "date": "2015-11-19"
    },
    "1.4.24": {
      "name": "1.4.24",
      "date": "2015-04-25"
    },
    "1.4.23": {
      "name": "1.4.23",
      "date": "2015-04-19"
    },
    "1.4.22": {
      "name": "1.4.22",
      "date": "2014-12-31"
    },
    "1.4.21": {
      "name": "1.4.21",
      "date": "2014-10-12"
    },
    "1.4.20": {
      "name": "1.4.20",
      "date": "2014-05-11"
    },
    "1.4.19": {
      "name": "1.4.19",
      "date": "2014-05-01"
    },
    "1.4.18": {
      "name": "1.4.18",
      "date": "2014-04-17"
    },
    "1.4.17": {
      "name": "1.4.17",
      "date": "2013-12-20"
    },
    "1.4.16": {
      "name": "1.4.16",
      "date": "2013-12-09"
    },
    "1.4.15": {
      "name": "1.4.15",
      "date": "2012-09-03"
    },
    "1.4.14": {
      "name": "1.4.14",
      "date": "2012-07-30"
    },
    "1.4.13": {
      "name": "1.4.13",
      "date": "2012-02-02"
    },
    "1.4.12": {
      "name": "1.4.12",
      "date": "2012-02-01"
    },
    "1.4.11": {
      "name": "1.4.11",
      "date": "2012-01-16"
    },
    "1.4.10": {
      "name": "1.4.10",
      "date": "2011-11-09"
    },
    "1.4.9": {
      "name": "1.4.9",
      "date": "2011-10-18"
    },
    "1.4.8": {
      "name": "1.4.8",
      "date": "2011-10-04"
    },
    "1.4.7": {
      "name": "1.4.7",
      "date": "2011-08-16"
    },
    "1.4.6": {
      "name": "1.4.6",
      "date": "2011-07-15"
    },
    "1.4.5": {
      "name": "1.4.5",
      "date": "2010-04-03"
    },
    "1.4.4": {
      "name": "1.4.4",
      "date": "2009-11-26"
    },
    "1.4.3": {
      "name": "1.4.3",
      "date": "2009-11-07"
    },
    "1.4.2": {
      "name": "1.4.2",
      "date": "2009-10-11"
    },
    "1.4.1": {
      "name": "1.4.1",
      "date": "2009-08-29"
    },
    "1.4.0": {
      "name": "1.4.0",
      "date": "2009-07-09"
    },
    "1.2.8": {
      "name": "1.2.8",
      "date": "2009-04-11"
    },
    "1.3.3": {
      "name": "1.3.3",
      "date": "2009-04-03"
    },
    "1.2.7": {
      "name": "1.2.7",
      "date": "2009-04-03"
    },
    "1.3.2": {
      "name": "1.3.2",
      "date": "2009-03-11"
    },
    "1.2.3": {
      "name": "1.2.3",
      "date": "2009-03-03"
    },
    "1.2.2": {
      "name": "1.2.2",
      "date": "2009-03-03"
    },
    "1.2.1": {
      "name": "1.2.1",
      "date": "2009-03-03"
    },
    "1.2.0": {
      "name": "1.2.0",
      "date": "2009-03-03"
    },
    "1.2.6": {
      "name": "1.2.6",
      "date": "2009-03-02"
    },
    "1.2.5": {
      "name": "1.2.5",
      "date": "2009-03-02"
    },
    "1.2.4": {
      "name": "1.2.4",
      "date": "2009-03-02"
    }
  }
}