{
  "releases": {},
  "versions": {
    "7.2.4": {
      "name": "7.2.4",
      "date": "2025-02-26"
    },
    "6.4.19": {
      "name": "6.4.19",
      "date": "2025-02-26"
    },
    "7.2.3": {
      "name": "7.2.3",
      "date": "2025-01-29"
    },
    "7.1.11": {
      "name": "7.1.11",
      "date": "2025-01-29"
    },
    "6.4.18": {
      "name": "6.4.18",
      "date": "2025-01-29"
    },
    "7.2.2": {
      "name": "7.2.2",
      "date": "2024-12-31"
    },
    "7.1.10": {
      "name": "7.1.10",
      "date": "2024-12-31"
    },
    "6.4.17": {
      "name": "6.4.17",
      "date": "2024-12-31"
    },
    "7.2.1": {
      "name": "7.2.1",
      "date": "2024-12-11"
    },
    "7.2.0": {
      "name": "7.2.0",
      "date": "2024-11-29"
    },
    "5.4.49": {
      "name": "5.4.49",
      "date": "2024-11-29"
    },
    "7.1.9": {
      "name": "7.1.9",
      "date": "2024-11-27"
    },
    "6.4.16": {
      "name": "6.4.16",
      "date": "2024-11-27"
    },
    "5.4.48": {
      "name": "5.4.48",
      "date": "2024-11-27"
    },
    "7.1.8": {
      "name": "7.1.8",
      "date": "2024-11-13"
    },
    "6.4.15": {
      "name": "6.4.15",
      "date": "2024-11-13"
    },
    "5.4.47": {
      "name": "5.4.47",
      "date": "2024-11-13"
    },
    "7.1.7": {
      "name": "7.1.7",
      "date": "2024-11-06"
    },
    "6.4.14": {
      "name": "6.4.14",
      "date": "2024-11-06"
    },
    "5.4.46": {
      "name": "5.4.46",
      "date": "2024-11-06"
    },
    "7.1.6": {
      "name": "7.1.6",
      "date": "2024-10-27"
    },
    "6.4.13": {
      "name": "6.4.13",
      "date": "2024-10-27"
    },
    "5.4.45": {
      "name": "5.4.45",
      "date": "2024-10-27"
    },
    "7.1.5": {
      "name": "7.1.5",
      "date": "2024-09-21"
    },
    "6.4.12": {
      "name": "6.4.12",
      "date": "2024-09-21"
    },
    "5.4.44": {
      "name": "5.4.44",
      "date": "2024-09-21"
    },
    "7.1.4": {
      "name": "7.1.4",
      "date": "2024-08-30"
    },
    "6.4.11": {
      "name": "6.4.11",
      "date": "2024-08-30"
    },
    "5.4.43": {
      "name": "5.4.43",
      "date": "2024-08-30"
    },
    "7.1.3": {
      "name": "7.1.3",
      "date": "2024-07-26"
    },
    "7.0.10": {
      "name": "7.0.10",
      "date": "2024-07-26"
    },
    "6.4.10": {
      "name": "6.4.10",
      "date": "2024-07-26"
    },
    "5.4.42": {
      "name": "5.4.42",
      "date": "2024-07-26"
    },
    "7.1.2": {
      "name": "7.1.2",
      "date": "2024-06-28"
    },
    "7.0.9": {
      "name": "7.0.9",
      "date": "2024-06-28"
    },
    "6.4.9": {
      "name": "6.4.9",
      "date": "2024-06-28"
    },
    "5.4.41": {
      "name": "5.4.41",
      "date": "2024-06-28"
    },
    "7.1.1": {
      "name": "7.1.1",
      "date": "2024-06-04"
    },
    "7.0.8": {
      "name": "7.0.8",
      "date": "2024-06-02"
    },
    "6.4.8": {
      "name": "6.4.8",
      "date": "2024-06-02"
    },
    "5.4.40": {
      "name": "5.4.40",
      "date": "2024-06-02"
    },
    "7.1.0": {
      "name": "7.1.0",
      "date": "2024-05-31"
    },
    "7.0.7": {
      "name": "7.0.7",
      "date": "2024-04-29"
    },
    "6.4.7": {
      "name": "6.4.7",
      "date": "2024-04-29"
    },
    "5.4.39": {
      "name": "5.4.39",
      "date": "2024-04-29"
    },
    "7.0.6": {
      "name": "7.0.6",
      "date": "2024-04-03"
    },
    "6.4.6": {
      "name": "6.4.6",
      "date": "2024-04-03"
    },
    "5.4.38": {
      "name": "5.4.38",
      "date": "2024-04-02"
    },
    "7.0.5": {
      "name": "7.0.5",
      "date": "2024-03-04"
    },
    "6.4.5": {
      "name": "6.4.5",
      "date": "2024-03-04"
    },
    "5.4.37": {
      "name": "5.4.37",
      "date": "2024-03-04"
    },
    "7.0.4": {
      "name": "7.0.4",
      "date": "2024-02-27"
    },
    "6.4.4": {
      "name": "6.4.4",
      "date": "2024-02-27"
    },
    "5.4.36": {
      "name": "5.4.36",
      "date": "2024-02-27"
    },
    "7.0.3": {
      "name": "7.0.3",
      "date": "2024-01-31"
    },
    "6.4.3": {
      "name": "6.4.3",
      "date": "2024-01-31"
    },
    "6.3.12": {
      "name": "6.3.12",
      "date": "2024-01-30"
    },
    "5.4.35": {
      "name": "5.4.35",
      "date": "2024-01-30"
    },
    "7.0.2": {
      "name": "7.0.2",
      "date": "2023-12-30"
    },
    "6.4.2": {
      "name": "6.4.2",
      "date": "2023-12-30"
    },
    "6.3.11": {
      "name": "6.3.11",
      "date": "2023-12-30"
    },
    "5.4.34": {
      "name": "5.4.34",
      "date": "2023-12-30"
    },
    "7.0.1": {
      "name": "7.0.1",
      "date": "2023-12-01"
    },
    "6.4.1": {
      "name": "6.4.1",
      "date": "2023-12-01"
    },
    "6.3.10": {
      "name": "6.3.10",
      "date": "2023-12-01"
    },
    "5.4.33": {
      "name": "5.4.33",
      "date": "2023-12-01"
    },
    "7.0.0": {
      "name": "7.0.0",
      "date": "2023-11-29"
    },
    "6.4.0": {
      "name": "6.4.0",
      "date": "2023-11-29"
    },
    "6.3.9": {
      "name": "6.3.9",
      "date": "2023-11-29"
    },
    "5.4.32": {
      "name": "5.4.32",
      "date": "2023-11-29"
    },
    "6.3.8": {
      "name": "6.3.8",
      "date": "2023-11-10"
    },
    "5.4.31": {
      "name": "5.4.31",
      "date": "2023-11-10"
    },
    "4.4.51": {
      "name": "4.4.51",
      "date": "2023-11-10"
    },
    "6.3.7": {
      "name": "6.3.7",
      "date": "2023-10-29"
    },
    "5.4.30": {
      "name": "5.4.30",
      "date": "2023-10-28"
    },
    "6.3.6": {
      "name": "6.3.6",
      "date": "2023-10-21"
    },
    "6.3.5": {
      "name": "6.3.5",
      "date": "2023-09-30"
    },
    "5.4.29": {
      "name": "5.4.29",
      "date": "2023-09-30"
    },
    "6.3.4": {
      "name": "6.3.4",
      "date": "2023-08-26"
    },
    "5.4.28": {
      "name": "5.4.28",
      "date": "2023-08-26"
    },
    "6.3.3": {
      "name": "6.3.3",
      "date": "2023-07-31"
    },
    "6.2.14": {
      "name": "6.2.14",
      "date": "2023-07-31"
    },
    "5.4.27": {
      "name": "5.4.27",
      "date": "2023-07-31"
    },
    "6.3.2": {
      "name": "6.3.2",
      "date": "2023-07-30"
    },
    "6.2.13": {
      "name": "6.2.13",
      "date": "2023-07-30"
    },
    "5.4.26": {
      "name": "5.4.26",
      "date": "2023-07-29"
    },
    "6.3.1": {
      "name": "6.3.1",
      "date": "2023-06-26"
    },
    "6.2.12": {
      "name": "6.2.12",
      "date": "2023-06-26"
    },
    "5.4.25": {
      "name": "5.4.25",
      "date": "2023-06-26"
    },
    "6.3.0": {
      "name": "6.3.0",
      "date": "2023-05-30"
    },
    "6.2.11": {
      "name": "6.2.11",
      "date": "2023-05-27"
    },
    "5.4.24": {
      "name": "5.4.24",
      "date": "2023-05-27"
    },
    "6.2.10": {
      "name": "6.2.10",
      "date": "2023-04-28"
    },
    "5.4.23": {
      "name": "5.4.23",
      "date": "2023-04-28"
    },
    "6.2.9": {
      "name": "6.2.9",
      "date": "2023-04-13"
    },
    "6.2.8": {
      "name": "6.2.8",
      "date": "2023-03-31"
    },
    "5.4.22": {
      "name": "5.4.22",
      "date": "2023-03-31"
    },
    "6.2.7": {
      "name": "6.2.7",
      "date": "2023-02-28"
    },
    "5.4.21": {
      "name": "5.4.21",
      "date": "2023-02-28"
    },
    "6.2.6": {
      "name": "6.2.6",
      "date": "2023-02-01"
    },
    "6.1.12": {
      "name": "6.1.12",
      "date": "2023-02-01"
    },
    "6.0.20": {
      "name": "6.0.20",
      "date": "2023-02-01"
    },
    "5.4.20": {
      "name": "5.4.20",
      "date": "2023-02-01"
    },
    "4.4.50": {
      "name": "4.4.50",
      "date": "2023-02-01"
    },
    "6.2.5": {
      "name": "6.2.5",
      "date": "2023-01-24"
    },
    "6.1.11": {
      "name": "6.1.11",
      "date": "2023-01-24"
    },
    "6.0.19": {
      "name": "6.0.19",
      "date": "2023-01-24"
    },
    "5.4.19": {
      "name": "5.4.19",
      "date": "2023-01-24"
    },
    "6.2.4": {
      "name": "6.2.4",
      "date": "2022-12-29"
    },
    "6.1.10": {
      "name": "6.1.10",
      "date": "2022-12-29"
    },
    "6.0.18": {
      "name": "6.0.18",
      "date": "2022-12-29"
    },
    "5.4.18": {
      "name": "5.4.18",
      "date": "2022-12-29"
    },
    "6.2.3": {
      "name": "6.2.3",
      "date": "2022-12-28"
    },
    "6.1.9": {
      "name": "6.1.9",
      "date": "2022-12-28"
    },
    "6.0.17": {
      "name": "6.0.17",
      "date": "2022-12-28"
    },
    "5.4.17": {
      "name": "5.4.17",
      "date": "2022-12-28"
    },
    "6.2.2": {
      "name": "6.2.2",
      "date": "2022-12-16"
    },
    "6.2.1": {
      "name": "6.2.1",
      "date": "2022-12-06"
    },
    "6.2.0": {
      "name": "6.2.0",
      "date": "2022-11-30"
    },
    "6.1.8": {
      "name": "6.1.8",
      "date": "2022-11-28"
    },
    "6.0.16": {
      "name": "6.0.16",
      "date": "2022-11-28"
    },
    "5.4.16": {
      "name": "5.4.16",
      "date": "2022-11-28"
    },
    "4.4.49": {
      "name": "4.4.49",
      "date": "2022-11-28"
    },
    "6.1.7": {
      "name": "6.1.7",
      "date": "2022-10-28"
    },
    "6.0.15": {
      "name": "6.0.15",
      "date": "2022-10-28"
    },
    "5.4.15": {
      "name": "5.4.15",
      "date": "2022-10-28"
    },
    "4.4.48": {
      "name": "4.4.48",
      "date": "2022-10-28"
    },
    "6.1.6": {
      "name": "6.1.6",
      "date": "2022-10-12"
    },
    "6.0.14": {
      "name": "6.0.14",
      "date": "2022-10-12"
    },
    "5.4.14": {
      "name": "5.4.14",
      "date": "2022-10-12"
    },
    "4.4.47": {
      "name": "4.4.47",
      "date": "2022-10-12"
    },
    "6.1.5": {
      "name": "6.1.5",
      "date": "2022-09-30"
    },
    "6.0.13": {
      "name": "6.0.13",
      "date": "2022-09-30"
    },
    "5.4.13": {
      "name": "5.4.13",
      "date": "2022-09-30"
    },
    "4.4.46": {
      "name": "4.4.46",
      "date": "2022-09-30"
    },
    "6.1.4": {
      "name": "6.1.4",
      "date": "2022-08-26"
    },
    "6.0.12": {
      "name": "6.0.12",
      "date": "2022-08-26"
    },
    "5.4.12": {
      "name": "5.4.12",
      "date": "2022-08-26"
    },
    "4.4.45": {
      "name": "4.4.45",
      "date": "2022-08-26"
    },
    "6.1.3": {
      "name": "6.1.3",
      "date": "2022-07-29"
    },
    "6.0.11": {
      "name": "6.0.11",
      "date": "2022-07-29"
    },
    "5.4.11": {
      "name": "5.4.11",
      "date": "2022-07-29"
    },
    "4.4.44": {
      "name": "4.4.44",
      "date": "2022-07-29"
    },
    "6.1.2": {
      "name": "6.1.2",
      "date": "2022-06-26"
    },
    "6.0.10": {
      "name": "6.0.10",
      "date": "2022-06-26"
    },
    "5.4.10": {
      "name": "5.4.10",
      "date": "2022-06-26"
    },
    "4.4.43": {
      "name": "4.4.43",
      "date": "2022-06-26"
    },
    "6.1.1": {
      "name": "6.1.1",
      "date": "2022-06-09"
    },
    "6.1.0": {
      "name": "6.1.0",
      "date": "2022-05-27"
    },
    "6.0.9": {
      "name": "6.0.9",
      "date": "2022-05-27"
    },
    "5.4.9": {
      "name": "5.4.9",
      "date": "2022-05-27"
    },
    "4.4.42": {
      "name": "4.4.42",
      "date": "2022-05-27"
    },
    "6.0.8": {
      "name": "6.0.8",
      "date": "2022-04-27"
    },
    "5.4.8": {
      "name": "5.4.8",
      "date": "2022-04-27"
    },
    "4.4.41": {
      "name": "4.4.41",
      "date": "2022-04-27"
    },
    "6.0.7": {
      "name": "6.0.7",
      "date": "2022-04-02"
    },
    "5.4.7": {
      "name": "5.4.7",
      "date": "2022-04-02"
    },
    "4.4.40": {
      "name": "4.4.40",
      "date": "2022-04-02"
    },
    "6.0.6": {
      "name": "6.0.6",
      "date": "2022-03-05"
    },
    "5.4.6": {
      "name": "5.4.6",
      "date": "2022-03-05"
    },
    "4.4.39": {
      "name": "4.4.39",
      "date": "2022-03-05"
    },
    "5.3.16": {
      "name": "5.3.16",
      "date": "2022-03-01"
    },
    "6.0.5": {
      "name": "6.0.5",
      "date": "2022-02-28"
    },
    "5.4.5": {
      "name": "5.4.5",
      "date": "2022-02-28"
    },
    "4.4.38": {
      "name": "4.4.38",
      "date": "2022-02-28"
    },
    "6.0.4": {
      "name": "6.0.4",
      "date": "2022-01-29"
    },
    "5.4.4": {
      "name": "5.4.4",
      "date": "2022-01-29"
    },
    "5.3.15": {
      "name": "5.3.15",
      "date": "2022-01-29"
    },
    "6.0.3": {
      "name": "6.0.3",
      "date": "2022-01-28"
    },
    "5.4.3": {
      "name": "5.4.3",
      "date": "2022-01-28"
    },
    "5.3.14": {
      "name": "5.3.14",
      "date": "2022-01-28"
    },
    "4.4.37": {
      "name": "4.4.37",
      "date": "2022-01-28"
    },
    "6.0.2": {
      "name": "6.0.2",
      "date": "2021-12-29"
    },
    "5.4.2": {
      "name": "5.4.2",
      "date": "2021-12-29"
    },
    "5.3.13": {
      "name": "5.3.13",
      "date": "2021-12-29"
    },
    "4.4.36": {
      "name": "4.4.36",
      "date": "2021-12-29"
    },
    "6.0.1": {
      "name": "6.0.1",
      "date": "2021-12-09"
    },
    "5.4.1": {
      "name": "5.4.1",
      "date": "2021-12-09"
    },
    "6.0.0": {
      "name": "6.0.0",
      "date": "2021-11-29"
    },
    "5.4.0": {
      "name": "5.4.0",
      "date": "2021-11-29"
    },
    "5.3.12": {
      "name": "5.3.12",
      "date": "2021-11-24"
    },
    "4.4.35": {
      "name": "4.4.35",
      "date": "2021-11-24"
    },
    "5.3.11": {
      "name": "5.3.11",
      "date": "2021-11-22"
    },
    "4.4.34": {
      "name": "4.4.34",
      "date": "2021-11-22"
    },
    "5.3.10": {
      "name": "5.3.10",
      "date": "2021-10-29"
    },
    "4.4.33": {
      "name": "4.4.33",
      "date": "2021-10-29"
    },
    "5.3.9": {
      "name": "5.3.9",
      "date": "2021-09-28"
    },
    "5.3.8": {
      "name": "5.3.8",
      "date": "2021-09-28"
    },
    "4.4.32": {
      "name": "4.4.32",
      "date": "2021-09-28"
    },
    "4.4.31": {
      "name": "4.4.31",
      "date": "2021-09-28"
    },
    "5.3.7": {
      "name": "5.3.7",
      "date": "2021-08-30"
    },
    "4.4.30": {
      "name": "4.4.30",
      "date": "2021-08-30"
    },
    "5.3.6": {
      "name": "5.3.6",
      "date": "2021-07-29"
    },
    "5.2.14": {
      "name": "5.2.14",
      "date": "2021-07-29"
    },
    "4.4.29": {
      "name": "4.4.29",
      "date": "2021-07-29"
    },
    "5.3.5": {
      "name": "5.3.5",
      "date": "2021-07-27"
    },
    "5.2.13": {
      "name": "5.2.13",
      "date": "2021-07-27"
    },
    "4.4.28": {
      "name": "4.4.28",
      "date": "2021-07-27"
    },
    "5.3.4": {
      "name": "5.3.4",
      "date": "2021-07-26"
    },
    "5.2.12": {
      "name": "5.2.12",
      "date": "2021-07-26"
    },
    "4.4.27": {
      "name": "4.4.27",
      "date": "2021-07-26"
    },
    "5.3.3": {
      "name": "5.3.3",
      "date": "2021-06-30"
    },
    "5.2.11": {
      "name": "5.2.11",
      "date": "2021-06-30"
    },
    "4.4.26": {
      "name": "4.4.26",
      "date": "2021-06-30"
    },
    "5.3.2": {
      "name": "5.3.2",
      "date": "2021-06-17"
    },
    "5.3.1": {
      "name": "5.3.1",
      "date": "2021-06-02"
    },
    "5.2.10": {
      "name": "5.2.10",
      "date": "2021-06-01"
    },
    "4.4.25": {
      "name": "4.4.25",
      "date": "2021-06-01"
    },
    "5.3.0": {
      "name": "5.3.0",
      "date": "2021-05-31"
    },
    "5.2.9": {
      "name": "5.2.9",
      "date": "2021-05-19"
    },
    "4.4.24": {
      "name": "4.4.24",
      "date": "2021-05-19"
    },
    "3.4.49": {
      "name": "3.4.49",
      "date": "2021-05-19"
    },
    "5.2.8": {
      "name": "5.2.8",
      "date": "2021-05-12"
    },
    "4.4.23": {
      "name": "4.4.23",
      "date": "2021-05-12"
    },
    "3.4.48": {
      "name": "3.4.48",
      "date": "2021-05-12"
    },
    "5.2.7": {
      "name": "5.2.7",
      "date": "2021-05-01"
    },
    "4.4.22": {
      "name": "4.4.22",
      "date": "2021-05-01"
    },
    "5.2.6": {
      "name": "5.2.6",
      "date": "2021-03-29"
    },
    "4.4.21": {
      "name": "4.4.21",
      "date": "2021-03-29"
    },
    "5.2.5": {
      "name": "5.2.5",
      "date": "2021-03-10"
    },
    "5.2.4": {
      "name": "5.2.4",
      "date": "2021-03-04"
    },
    "4.4.20": {
      "name": "4.4.20",
      "date": "2021-03-04"
    },
    "5.2.3": {
      "name": "5.2.3",
      "date": "2021-02-03"
    },
    "5.2.2": {
      "name": "5.2.2",
      "date": "2021-01-27"
    },
    "5.1.11": {
      "name": "5.1.11",
      "date": "2021-01-27"
    },
    "4.4.19": {
      "name": "4.4.19",
      "date": "2021-01-27"
    },
    "5.2.1": {
      "name": "5.2.1",
      "date": "2020-12-18"
    },
    "5.1.10": {
      "name": "5.1.10",
      "date": "2020-12-18"
    },
    "4.4.18": {
      "name": "4.4.18",
      "date": "2020-12-18"
    },
    "5.2.0": {
      "name": "5.2.0",
      "date": "2020-11-30"
    },
    "5.1.9": {
      "name": "5.1.9",
      "date": "2020-11-29"
    },
    "4.4.17": {
      "name": "4.4.17",
      "date": "2020-11-29"
    },
    "3.4.47": {
      "name": "3.4.47",
      "date": "2020-11-27"
    },
    "5.1.8": {
      "name": "5.1.8",
      "date": "2020-10-28"
    },
    "4.4.16": {
      "name": "4.4.16",
      "date": "2020-10-28"
    },
    "3.4.46": {
      "name": "3.4.46",
      "date": "2020-10-28"
    },
    "5.1.7": {
      "name": "5.1.7",
      "date": "2020-10-04"
    },
    "4.4.15": {
      "name": "4.4.15",
      "date": "2020-10-04"
    },
    "5.1.6": {
      "name": "5.1.6",
      "date": "2020-09-27"
    },
    "4.4.14": {
      "name": "4.4.14",
      "date": "2020-09-27"
    },
    "3.4.45": {
      "name": "3.4.45",
      "date": "2020-09-27"
    },
    "5.1.5": {
      "name": "5.1.5",
      "date": "2020-09-02"
    },
    "4.4.13": {
      "name": "4.4.13",
      "date": "2020-09-02"
    },
    "5.1.4": {
      "name": "5.1.4",
      "date": "2020-08-31"
    },
    "4.4.12": {
      "name": "4.4.12",
      "date": "2020-08-31"
    },
    "3.4.44": {
      "name": "3.4.44",
      "date": "2020-08-31"
    },
    "5.1.3": {
      "name": "5.1.3",
      "date": "2020-07-24"
    },
    "5.0.11": {
      "name": "5.0.11",
      "date": "2020-07-24"
    },
    "4.4.11": {
      "name": "4.4.11",
      "date": "2020-07-24"
    },
    "3.4.43": {
      "name": "3.4.43",
      "date": "2020-07-24"
    },
    "5.1.2": {
      "name": "5.1.2",
      "date": "2020-06-15"
    },
    "5.1.1": {
      "name": "5.1.1",
      "date": "2020-06-12"
    },
    "5.0.10": {
      "name": "5.0.10",
      "date": "2020-06-12"
    },
    "4.4.10": {
      "name": "4.4.10",
      "date": "2020-06-12"
    },
    "3.4.42": {
      "name": "3.4.42",
      "date": "2020-06-12"
    },
    "5.1.0": {
      "name": "5.1.0",
      "date": "2020-05-31"
    },
    "5.0.9": {
      "name": "5.0.9",
      "date": "2020-05-31"
    },
    "4.4.9": {
      "name": "4.4.9",
      "date": "2020-05-31"
    },
    "3.4.41": {
      "name": "3.4.41",
      "date": "2020-05-31"
    },
    "5.0.8": {
      "name": "5.0.8",
      "date": "2020-04-28"
    },
    "4.4.8": {
      "name": "4.4.8",
      "date": "2020-04-28"
    },
    "3.4.40": {
      "name": "3.4.40",
      "date": "2020-04-28"
    },
    "5.0.7": {
      "name": "5.0.7",
      "date": "2020-03-30"
    },
    "4.4.7": {
      "name": "4.4.7",
      "date": "2020-03-30"
    },
    "3.4.39": {
      "name": "3.4.39",
      "date": "2020-03-30"
    },
    "5.0.6": {
      "name": "5.0.6",
      "date": "2020-03-27"
    },
    "4.4.6": {
      "name": "4.4.6",
      "date": "2020-03-27"
    },
    "5.0.5": {
      "name": "5.0.5",
      "date": "2020-02-29"
    },
    "4.4.5": {
      "name": "4.4.5",
      "date": "2020-02-29"
    },
    "3.4.38": {
      "name": "3.4.38",
      "date": "2020-02-29"
    },
    "5.0.4": {
      "name": "5.0.4",
      "date": "2020-01-31"
    },
    "4.4.4": {
      "name": "4.4.4",
      "date": "2020-01-31"
    },
    "4.3.11": {
      "name": "4.3.11",
      "date": "2020-01-31"
    },
    "5.0.3": {
      "name": "5.0.3",
      "date": "2020-01-21"
    },
    "4.4.3": {
      "name": "4.4.3",
      "date": "2020-01-21"
    },
    "4.3.10": {
      "name": "4.3.10",
      "date": "2020-01-21"
    },
    "3.4.37": {
      "name": "3.4.37",
      "date": "2020-01-21"
    },
    "5.0.2": {
      "name": "5.0.2",
      "date": "2019-12-19"
    },
    "4.4.2": {
      "name": "4.4.2",
      "date": "2019-12-19"
    },
    "5.0.1": {
      "name": "5.0.1",
      "date": "2019-12-01"
    },
    "4.4.1": {
      "name": "4.4.1",
      "date": "2019-12-01"
    },
    "4.3.9": {
      "name": "4.3.9",
      "date": "2019-12-01"
    },
    "3.4.36": {
      "name": "3.4.36",
      "date": "2019-12-01"
    },
    "5.0.0": {
      "name": "5.0.0",
      "date": "2019-11-21"
    },
    "4.4.0": {
      "name": "4.4.0",
      "date": "2019-11-21"
    },
    "4.3.8": {
      "name": "4.3.8",
      "date": "2019-11-13"
    },
    "4.2.12": {
      "name": "4.2.12",
      "date": "2019-11-13"
    },
    "3.4.35": {
      "name": "3.4.35",
      "date": "2019-11-13"
    },
    "2.8.52": {
      "name": "2.8.52",
      "date": "2019-11-13"
    },
    "4.3.7": {
      "name": "4.3.7",
      "date": "2019-11-11"
    },
    "3.4.34": {
      "name": "3.4.34",
      "date": "2019-11-11"
    },
    "4.3.6": {
      "name": "4.3.6",
      "date": "2019-11-01"
    },
    "3.4.33": {
      "name": "3.4.33",
      "date": "2019-11-01"
    },
    "4.3.5": {
      "name": "4.3.5",
      "date": "2019-10-07"
    },
    "3.4.32": {
      "name": "3.4.32",
      "date": "2019-10-07"
    },
    "4.3.4": {
      "name": "4.3.4",
      "date": "2019-08-26"
    },
    "3.4.31": {
      "name": "3.4.31",
      "date": "2019-08-26"
    },
    "4.3.3": {
      "name": "4.3.3",
      "date": "2019-07-28"
    },
    "4.2.11": {
      "name": "4.2.11",
      "date": "2019-07-28"
    },
    "3.4.30": {
      "name": "3.4.30",
      "date": "2019-07-27"
    },
    "4.3.2": {
      "name": "4.3.2",
      "date": "2019-06-26"
    },
    "4.2.10": {
      "name": "4.2.10",
      "date": "2019-06-26"
    },
    "3.4.29": {
      "name": "3.4.29",
      "date": "2019-06-26"
    },
    "4.3.1": {
      "name": "4.3.1",
      "date": "2019-06-06"
    },
    "4.3.0": {
      "name": "4.3.0",
      "date": "2019-05-30"
    },
    "4.2.9": {
      "name": "4.2.9",
      "date": "2019-05-28"
    },
    "3.4.28": {
      "name": "3.4.28",
      "date": "2019-05-28"
    },
    "4.2.8": {
      "name": "4.2.8",
      "date": "2019-05-01"
    },
    "3.4.27": {
      "name": "3.4.27",
      "date": "2019-05-01"
    },
    "4.2.7": {
      "name": "4.2.7",
      "date": "2019-04-17"
    },
    "4.1.13": {
      "name": "4.1.13",
      "date": "2019-04-17"
    },
    "4.1.12": {
      "name": "4.1.12",
      "date": "2019-04-17"
    },
    "3.4.26": {
      "name": "3.4.26",
      "date": "2019-04-17"
    },
    "2.8.51": {
      "name": "2.8.51",
      "date": "2019-04-17"
    },
    "2.8.50": {
      "name": "2.8.50",
      "date": "2019-04-17"
    },
    "2.7.52": {
      "name": "2.7.52",
      "date": "2019-04-17"
    },
    "2.7.51": {
      "name": "2.7.51",
      "date": "2019-04-17"
    },
    "4.2.6": {
      "name": "4.2.6",
      "date": "2019-04-16"
    },
    "3.4.25": {
      "name": "3.4.25",
      "date": "2019-04-16"
    },
    "4.2.5": {
      "name": "4.2.5",
      "date": "2019-04-02"
    },
    "3.4.24": {
      "name": "3.4.24",
      "date": "2019-04-02"
    },
    "4.2.4": {
      "name": "4.2.4",
      "date": "2019-03-03"
    },
    "3.4.23": {
      "name": "3.4.23",
      "date": "2019-03-03"
    },
    "4.2.3": {
      "name": "4.2.3",
      "date": "2019-02-03"
    },
    "3.4.22": {
      "name": "3.4.22",
      "date": "2019-02-03"
    },
    "4.1.11": {
      "name": "4.1.11",
      "date": "2019-01-29"
    },
    "4.2.2": {
      "name": "4.2.2",
      "date": "2019-01-06"
    },
    "4.1.10": {
      "name": "4.1.10",
      "date": "2019-01-06"
    },
    "3.4.21": {
      "name": "3.4.21",
      "date": "2019-01-06"
    },
    "4.2.1": {
      "name": "4.2.1",
      "date": "2018-12-06"
    },
    "4.1.9": {
      "name": "4.1.9",
      "date": "2018-12-06"
    },
    "4.0.15": {
      "name": "4.0.15",
      "date": "2018-12-06"
    },
    "3.4.20": {
      "name": "3.4.20",
      "date": "2018-12-06"
    },
    "2.8.49": {
      "name": "2.8.49",
      "date": "2018-12-06"
    },
    "2.7.50": {
      "name": "2.7.50",
      "date": "2018-12-06"
    },
    "4.2.0": {
      "name": "4.2.0",
      "date": "2018-11-30"
    },
    "4.1.8": {
      "name": "4.1.8",
      "date": "2018-11-26"
    },
    "3.4.19": {
      "name": "3.4.19",
      "date": "2018-11-26"
    },
    "2.8.48": {
      "name": "2.8.48",
      "date": "2018-11-26"
    },
    "4.1.7": {
      "name": "4.1.7",
      "date": "2018-11-03"
    },
    "3.4.18": {
      "name": "3.4.18",
      "date": "2018-11-03"
    },
    "2.8.47": {
      "name": "2.8.47",
      "date": "2018-11-03"
    },
    "4.1.6": {
      "name": "4.1.6",
      "date": "2018-10-03"
    },
    "3.4.17": {
      "name": "3.4.17",
      "date": "2018-10-03"
    },
    "4.1.5": {
      "name": "4.1.5",
      "date": "2018-09-30"
    },
    "3.4.16": {
      "name": "3.4.16",
      "date": "2018-09-30"
    },
    "2.8.46": {
      "name": "2.8.46",
      "date": "2018-09-30"
    },
    "4.1.4": {
      "name": "4.1.4",
      "date": "2018-08-28"
    },
    "3.4.15": {
      "name": "3.4.15",
      "date": "2018-08-28"
    },
    "2.8.45": {
      "name": "2.8.45",
      "date": "2018-08-27"
    },
    "4.1.3": {
      "name": "4.1.3",
      "date": "2018-08-01"
    },
    "4.0.14": {
      "name": "4.0.14",
      "date": "2018-08-01"
    },
    "3.4.14": {
      "name": "3.4.14",
      "date": "2018-08-01"
    },
    "3.3.18": {
      "name": "3.3.18",
      "date": "2018-08-01"
    },
    "2.8.44": {
      "name": "2.8.44",
      "date": "2018-08-01"
    },
    "2.7.49": {
      "name": "2.7.49",
      "date": "2018-08-01"
    },
    "4.1.2": {
      "name": "4.1.2",
      "date": "2018-07-23"
    },
    "4.0.13": {
      "name": "4.0.13",
      "date": "2018-07-23"
    },
    "3.4.13": {
      "name": "3.4.13",
      "date": "2018-07-23"
    },
    "2.8.43": {
      "name": "2.8.43",
      "date": "2018-07-23"
    },
    "4.1.1": {
      "name": "4.1.1",
      "date": "2018-06-25"
    },
    "4.0.12": {
      "name": "4.0.12",
      "date": "2018-06-25"
    },
    "3.4.12": {
      "name": "3.4.12",
      "date": "2018-06-25"
    },
    "2.8.42": {
      "name": "2.8.42",
      "date": "2018-06-25"
    },
    "4.1.0": {
      "name": "4.1.0",
      "date": "2018-05-30"
    },
    "4.0.11": {
      "name": "4.0.11",
      "date": "2018-05-25"
    },
    "3.4.11": {
      "name": "3.4.11",
      "date": "2018-05-25"
    },
    "3.3.17": {
      "name": "3.3.17",
      "date": "2018-05-25"
    },
    "2.8.41": {
      "name": "2.8.41",
      "date": "2018-05-25"
    },
    "2.7.48": {
      "name": "2.7.48",
      "date": "2018-05-25"
    },
    "4.0.10": {
      "name": "4.0.10",
      "date": "2018-05-21"
    },
    "3.4.10": {
      "name": "3.4.10",
      "date": "2018-05-21"
    },
    "2.8.40": {
      "name": "2.8.40",
      "date": "2018-05-21"
    },
    "2.7.47": {
      "name": "2.7.47",
      "date": "2018-05-21"
    },
    "4.0.9": {
      "name": "4.0.9",
      "date": "2018-04-30"
    },
    "3.4.9": {
      "name": "3.4.9",
      "date": "2018-04-30"
    },
    "2.8.39": {
      "name": "2.8.39",
      "date": "2018-04-30"
    },
    "2.7.46": {
      "name": "2.7.46",
      "date": "2018-04-27"
    },
    "4.0.8": {
      "name": "4.0.8",
      "date": "2018-04-06"
    },
    "3.4.8": {
      "name": "3.4.8",
      "date": "2018-04-06"
    },
    "2.8.38": {
      "name": "2.8.38",
      "date": "2018-04-06"
    },
    "2.7.45": {
      "name": "2.7.45",
      "date": "2018-04-06"
    },
    "4.0.7": {
      "name": "4.0.7",
      "date": "2018-04-03"
    },
    "3.4.7": {
      "name": "3.4.7",
      "date": "2018-04-03"
    },
    "2.8.37": {
      "name": "2.8.37",
      "date": "2018-04-02"
    },
    "2.7.44": {
      "name": "2.7.44",
      "date": "2018-04-02"
    },
    "4.0.6": {
      "name": "4.0.6",
      "date": "2018-03-05"
    },
    "3.4.6": {
      "name": "3.4.6",
      "date": "2018-03-05"
    },
    "2.8.36": {
      "name": "2.8.36",
      "date": "2018-03-05"
    },
    "2.7.43": {
      "name": "2.7.43",
      "date": "2018-03-05"
    },
    "4.0.5": {
      "name": "4.0.5",
      "date": "2018-03-01"
    },
    "3.4.5": {
      "name": "3.4.5",
      "date": "2018-03-01"
    },
    "2.8.35": {
      "name": "2.8.35",
      "date": "2018-03-01"
    },
    "2.7.42": {
      "name": "2.7.42",
      "date": "2018-02-28"
    },
    "4.0.4": {
      "name": "4.0.4",
      "date": "2018-01-29"
    },
    "3.4.4": {
      "name": "3.4.4",
      "date": "2018-01-29"
    },
    "3.3.16": {
      "name": "3.3.16",
      "date": "2018-01-29"
    },
    "2.8.34": {
      "name": "2.8.34",
      "date": "2018-01-29"
    },
    "2.7.41": {
      "name": "2.7.41",
      "date": "2018-01-29"
    },
    "4.0.3": {
      "name": "4.0.3",
      "date": "2018-01-05"
    },
    "3.4.3": {
      "name": "3.4.3",
      "date": "2018-01-05"
    },
    "3.3.15": {
      "name": "3.3.15",
      "date": "2018-01-05"
    },
    "2.8.33": {
      "name": "2.8.33",
      "date": "2018-01-05"
    },
    "2.7.40": {
      "name": "2.7.40",
      "date": "2018-01-05"
    },
    "4.0.2": {
      "name": "4.0.2",
      "date": "2017-12-14"
    },
    "3.4.2": {
      "name": "3.4.2",
      "date": "2017-12-14"
    },
    "4.0.1": {
      "name": "4.0.1",
      "date": "2017-12-04"
    },
    "3.4.1": {
      "name": "3.4.1",
      "date": "2017-12-04"
    },
    "3.3.14": {
      "name": "3.3.14",
      "date": "2017-12-04"
    },
    "2.8.32": {
      "name": "2.8.32",
      "date": "2017-12-04"
    },
    "2.7.39": {
      "name": "2.7.39",
      "date": "2017-12-04"
    },
    "4.0.0": {
      "name": "4.0.0",
      "date": "2017-11-30"
    },
    "3.4.0": {
      "name": "3.4.0",
      "date": "2017-11-30"
    },
    "3.3.13": {
      "name": "3.3.13",
      "date": "2017-11-16"
    },
    "3.2.14": {
      "name": "3.2.14",
      "date": "2017-11-16"
    },
    "2.8.31": {
      "name": "2.8.31",
      "date": "2017-11-16"
    },
    "2.7.38": {
      "name": "2.7.38",
      "date": "2017-11-16"
    },
    "3.3.12": {
      "name": "3.3.12",
      "date": "2017-11-13"
    },
    "2.8.30": {
      "name": "2.8.30",
      "date": "2017-11-13"
    },
    "2.7.37": {
      "name": "2.7.37",
      "date": "2017-11-13"
    },
    "3.3.11": {
      "name": "3.3.11",
      "date": "2017-11-10"
    },
    "2.8.29": {
      "name": "2.8.29",
      "date": "2017-11-10"
    },
    "2.7.36": {
      "name": "2.7.36",
      "date": "2017-11-10"
    },
    "3.3.10": {
      "name": "3.3.10",
      "date": "2017-10-05"
    },
    "2.8.28": {
      "name": "2.8.28",
      "date": "2017-10-05"
    },
    "2.7.35": {
      "name": "2.7.35",
      "date": "2017-10-05"
    },
    "3.3.9": {
      "name": "3.3.9",
      "date": "2017-09-11"
    },
    "3.3.8": {
      "name": "3.3.8",
      "date": "2017-08-28"
    },
    "3.3.7": {
      "name": "3.3.7",
      "date": "2017-08-28"
    },
    "2.8.27": {
      "name": "2.8.27",
      "date": "2017-08-28"
    },
    "2.7.34": {
      "name": "2.7.34",
      "date": "2017-08-28"
    },
    "3.3.6": {
      "name": "3.3.6",
      "date": "2017-08-01"
    },
    "3.2.13": {
      "name": "3.2.13",
      "date": "2017-08-01"
    },
    "2.8.26": {
      "name": "2.8.26",
      "date": "2017-08-01"
    },
    "2.7.33": {
      "name": "2.7.33",
      "date": "2017-08-01"
    },
    "3.3.5": {
      "name": "3.3.5",
      "date": "2017-07-17"
    },
    "3.2.12": {
      "name": "3.2.12",
      "date": "2017-07-17"
    },
    "2.8.25": {
      "name": "2.8.25",
      "date": "2017-07-17"
    },
    "2.7.32": {
      "name": "2.7.32",
      "date": "2017-07-17"
    },
    "3.3.4": {
      "name": "3.3.4",
      "date": "2017-07-05"
    },
    "3.2.11": {
      "name": "3.2.11",
      "date": "2017-07-05"
    },
    "2.8.24": {
      "name": "2.8.24",
      "date": "2017-07-05"
    },
    "2.7.31": {
      "name": "2.7.31",
      "date": "2017-07-05"
    },
    "3.3.3": {
      "name": "3.3.3",
      "date": "2017-07-04"
    },
    "3.2.10": {
      "name": "3.2.10",
      "date": "2017-07-04"
    },
    "2.8.23": {
      "name": "2.8.23",
      "date": "2017-07-04"
    },
    "2.7.30": {
      "name": "2.7.30",
      "date": "2017-07-03"
    },
    "2.8.22": {
      "name": "2.8.22",
      "date": "2017-06-07"
    },
    "2.7.29": {
      "name": "2.7.29",
      "date": "2017-06-07"
    },
    "3.3.2": {
      "name": "3.3.2",
      "date": "2017-06-05"
    },
    "3.3.1": {
      "name": "3.3.1",
      "date": "2017-06-05"
    },
    "3.3.0": {
      "name": "3.3.0",
      "date": "2017-05-29"
    },
    "3.2.9": {
      "name": "3.2.9",
      "date": "2017-05-29"
    },
    "2.8.21": {
      "name": "2.8.21",
      "date": "2017-05-29"
    },
    "2.7.28": {
      "name": "2.7.28",
      "date": "2017-05-29"
    },
    "3.2.8": {
      "name": "3.2.8",
      "date": "2017-05-01"
    },
    "2.8.20": {
      "name": "2.8.20",
      "date": "2017-05-01"
    },
    "2.7.27": {
      "name": "2.7.27",
      "date": "2017-05-01"
    },
    "3.2.7": {
      "name": "3.2.7",
      "date": "2017-04-05"
    },
    "2.8.19": {
      "name": "2.8.19",
      "date": "2017-04-04"
    },
    "2.7.26": {
      "name": "2.7.26",
      "date": "2017-04-03"
    },
    "3.2.6": {
      "name": "3.2.6",
      "date": "2017-03-10"
    },
    "3.2.5": {
      "name": "3.2.5",
      "date": "2017-03-08"
    },
    "2.8.18": {
      "name": "2.8.18",
      "date": "2017-03-05"
    },
    "2.7.25": {
      "name": "2.7.25",
      "date": "2017-03-05"
    },
    "3.2.4": {
      "name": "3.2.4",
      "date": "2017-02-16"
    },
    "3.2.3": {
      "name": "3.2.3",
      "date": "2017-02-06"
    },
    "2.8.17": {
      "name": "2.8.17",
      "date": "2017-02-06"
    },
    "2.7.24": {
      "name": "2.7.24",
      "date": "2017-02-06"
    },
    "3.1.10": {
      "name": "3.1.10",
      "date": "2017-01-27"
    },
    "3.2.2": {
      "name": "3.2.2",
      "date": "2017-01-12"
    },
    "3.1.9": {
      "name": "3.1.9",
      "date": "2017-01-12"
    },
    "2.8.16": {
      "name": "2.8.16",
      "date": "2017-01-12"
    },
    "2.7.23": {
      "name": "2.7.23",
      "date": "2017-01-12"
    },
    "3.2.1": {
      "name": "3.2.1",
      "date": "2016-12-13"
    },
    "3.1.8": {
      "name": "3.1.8",
      "date": "2016-12-13"
    },
    "2.8.15": {
      "name": "2.8.15",
      "date": "2016-12-13"
    },
    "2.7.22": {
      "name": "2.7.22",
      "date": "2016-12-13"
    },
    "3.2.0": {
      "name": "3.2.0",
      "date": "2016-11-30"
    },
    "3.1.7": {
      "name": "3.1.7",
      "date": "2016-11-20"
    },
    "2.8.14": {
      "name": "2.8.14",
      "date": "2016-11-20"
    },
    "2.7.21": {
      "name": "2.7.21",
      "date": "2016-11-20"
    },
    "3.1.6": {
      "name": "3.1.6",
      "date": "2016-10-26"
    },
    "2.8.13": {
      "name": "2.8.13",
      "date": "2016-10-26"
    },
    "2.7.20": {
      "name": "2.7.20",
      "date": "2016-10-26"
    },
    "3.1.5": {
      "name": "3.1.5",
      "date": "2016-10-03"
    },
    "2.8.12": {
      "name": "2.8.12",
      "date": "2016-10-03"
    },
    "2.7.19": {
      "name": "2.7.19",
      "date": "2016-10-03"
    },
    "2.8.11": {
      "name": "2.8.11",
      "date": "2016-09-06"
    },
    "2.7.18": {
      "name": "2.7.18",
      "date": "2016-09-06"
    },
    "3.1.4": {
      "name": "3.1.4",
      "date": "2016-09-03"
    },
    "2.8.10": {
      "name": "2.8.10",
      "date": "2016-09-02"
    },
    "2.7.17": {
      "name": "2.7.17",
      "date": "2016-09-01"
    },
    "3.1.3": {
      "name": "3.1.3",
      "date": "2016-07-30"
    },
    "3.0.9": {
      "name": "3.0.9",
      "date": "2016-07-30"
    },
    "2.8.9": {
      "name": "2.8.9",
      "date": "2016-07-30"
    },
    "2.7.16": {
      "name": "2.7.16",
      "date": "2016-07-30"
    },
    "3.1.2": {
      "name": "3.1.2",
      "date": "2016-06-30"
    },
    "3.0.8": {
      "name": "3.0.8",
      "date": "2016-06-30"
    },
    "2.8.8": {
      "name": "2.8.8",
      "date": "2016-06-30"
    },
    "2.7.15": {
      "name": "2.7.15",
      "date": "2016-06-30"
    },
    "3.1.1": {
      "name": "3.1.1",
      "date": "2016-06-15"
    },
    "3.0.7": {
      "name": "3.0.7",
      "date": "2016-06-06"
    },
    "2.8.7": {
      "name": "2.8.7",
      "date": "2016-06-06"
    },
    "2.7.14": {
      "name": "2.7.14",
      "date": "2016-06-06"
    },
    "3.1.0": {
      "name": "3.1.0",
      "date": "2016-05-30"
    },
    "2.3.42": {
      "name": "2.3.42",
      "date": "2016-05-30"
    },
    "3.0.6": {
      "name": "3.0.6",
      "date": "2016-05-09"
    },
    "2.8.6": {
      "name": "2.8.6",
      "date": "2016-05-09"
    },
    "2.7.13": {
      "name": "2.7.13",
      "date": "2016-05-09"
    },
    "2.3.41": {
      "name": "2.3.41",
      "date": "2016-05-09"
    },
    "3.0.5": {
      "name": "3.0.5",
      "date": "2016-05-03"
    },
    "2.8.5": {
      "name": "2.8.5",
      "date": "2016-05-02"
    },
    "2.7.12": {
      "name": "2.7.12",
      "date": "2016-04-29"
    },
    "2.3.40": {
      "name": "2.3.40",
      "date": "2016-04-29"
    },
    "3.0.4": {
      "name": "3.0.4",
      "date": "2016-03-30"
    },
    "2.8.4": {
      "name": "2.8.4",
      "date": "2016-03-27"
    },
    "2.7.11": {
      "name": "2.7.11",
      "date": "2016-03-25"
    },
    "2.3.39": {
      "name": "2.3.39",
      "date": "2016-03-13"
    },
    "3.0.3": {
      "name": "3.0.3",
      "date": "2016-02-28"
    },
    "2.8.3": {
      "name": "2.8.3",
      "date": "2016-02-28"
    },
    "2.7.10": {
      "name": "2.7.10",
      "date": "2016-02-28"
    },
    "2.3.38": {
      "name": "2.3.38",
      "date": "2016-02-28"
    },
    "3.0.2": {
      "name": "3.0.2",
      "date": "2016-02-03"
    },
    "2.8.2": {
      "name": "2.8.2",
      "date": "2016-01-14"
    },
    "2.7.9": {
      "name": "2.7.9",
      "date": "2016-01-14"
    },
    "2.6.13": {
      "name": "2.6.13",
      "date": "2016-01-14"
    },
    "2.3.37": {
      "name": "2.3.37",
      "date": "2016-01-14"
    },
    "3.0.1": {
      "name": "3.0.1",
      "date": "2015-12-26"
    },
    "2.8.1": {
      "name": "2.8.1",
      "date": "2015-12-26"
    },
    "2.7.8": {
      "name": "2.7.8",
      "date": "2015-12-26"
    },
    "2.3.36": {
      "name": "2.3.36",
      "date": "2015-12-26"
    },
    "3.0.0": {
      "name": "3.0.0",
      "date": "2015-11-30"
    },
    "2.8.0": {
      "name": "2.8.0",
      "date": "2015-11-30"
    },
    "2.7.7": {
      "name": "2.7.7",
      "date": "2015-11-23"
    },
    "2.6.12": {
      "name": "2.6.12",
      "date": "2015-11-23"
    },
    "2.3.35": {
      "name": "2.3.35",
      "date": "2015-11-23"
    },
    "2.7.6": {
      "name": "2.7.6",
      "date": "2015-10-27"
    },
    "2.3.34": {
      "name": "2.3.34",
      "date": "2015-10-27"
    },
    "2.7.5": {
      "name": "2.7.5",
      "date": "2015-09-25"
    },
    "2.3.33": {
      "name": "2.3.33",
      "date": "2015-09-25"
    },
    "2.7.4": {
      "name": "2.7.4",
      "date": "2015-09-08"
    },
    "2.3.32": {
      "name": "2.3.32",
      "date": "2015-09-01"
    },
    "2.7.3": {
      "name": "2.7.3",
      "date": "2015-07-31"
    },
    "2.6.11": {
      "name": "2.6.11",
      "date": "2015-07-26"
    },
    "2.7.2": {
      "name": "2.7.2",
      "date": "2015-07-13"
    },
    "2.6.10": {
      "name": "2.6.10",
      "date": "2015-07-13"
    },
    "2.3.31": {
      "name": "2.3.31",
      "date": "2015-07-13"
    },
    "2.7.1": {
      "name": "2.7.1",
      "date": "2015-06-11"
    },
    "2.7.0": {
      "name": "2.7.0",
      "date": "2015-05-30"
    },
    "2.6.9": {
      "name": "2.6.9",
      "date": "2015-05-30"
    },
    "2.3.30": {
      "name": "2.3.30",
      "date": "2015-05-30"
    },
    "2.6.8": {
      "name": "2.6.8",
      "date": "2015-05-27"
    },
    "2.5.12": {
      "name": "2.5.12",
      "date": "2015-05-27"
    },
    "2.3.29": {
      "name": "2.3.29",
      "date": "2015-05-26"
    },
    "2.6.7": {
      "name": "2.6.7",
      "date": "2015-05-11"
    },
    "2.3.28": {
      "name": "2.3.28",
      "date": "2015-05-10"
    },
    "2.6.6": {
      "name": "2.6.6",
      "date": "2015-04-01"
    },
    "2.5.11": {
      "name": "2.5.11",
      "date": "2015-04-01"
    },
    "2.3.27": {
      "name": "2.3.27",
      "date": "2015-04-01"
    },
    "2.6.5": {
      "name": "2.6.5",
      "date": "2015-03-17"
    },
    "2.3.26": {
      "name": "2.3.26",
      "date": "2015-03-17"
    },
    "2.6.4": {
      "name": "2.6.4",
      "date": "2015-02-02"
    },
    "2.5.10": {
      "name": "2.5.10",
      "date": "2015-02-02"
    },
    "2.3.25": {
      "name": "2.3.25",
      "date": "2015-01-30"
    },
    "2.6.3": {
      "name": "2.6.3",
      "date": "2015-01-07"
    },
    "2.6.2": {
      "name": "2.6.2",
      "date": "2015-01-07"
    },
    "2.5.9": {
      "name": "2.5.9",
      "date": "2015-01-07"
    },
    "2.3.24": {
      "name": "2.3.24",
      "date": "2015-01-07"
    },
    "2.6.1": {
      "name": "2.6.1",
      "date": "2014-12-03"
    },
    "2.5.8": {
      "name": "2.5.8",
      "date": "2014-12-03"
    },
    "2.3.23": {
      "name": "2.3.23",
      "date": "2014-12-03"
    },
    "2.6.0": {
      "name": "2.6.0",
      "date": "2014-11-28"
    },
    "2.5.7": {
      "name": "2.5.7",
      "date": "2014-11-20"
    },
    "2.3.22": {
      "name": "2.3.22",
      "date": "2014-11-20"
    },
    "2.5.6": {
      "name": "2.5.6",
      "date": "2014-10-24"
    },
    "2.3.21": {
      "name": "2.3.21",
      "date": "2014-10-24"
    },
    "2.5.5": {
      "name": "2.5.5",
      "date": "2014-09-28"
    },
    "2.4.10": {
      "name": "2.4.10",
      "date": "2014-09-28"
    },
    "2.3.20": {
      "name": "2.3.20",
      "date": "2014-09-28"
    },
    "2.5.4": {
      "name": "2.5.4",
      "date": "2014-09-03"
    },
    "2.4.9": {
      "name": "2.4.9",
      "date": "2014-09-03"
    },
    "2.3.19": {
      "name": "2.3.19",
      "date": "2014-09-03"
    },
    "2.5.3": {
      "name": "2.5.3",
      "date": "2014-08-06"
    },
    "2.5.2": {
      "name": "2.5.2",
      "date": "2014-07-15"
    },
    "2.4.8": {
      "name": "2.4.8",
      "date": "2014-07-15"
    },
    "2.3.18": {
      "name": "2.3.18",
      "date": "2014-07-15"
    },
    "2.5.1": {
      "name": "2.5.1",
      "date": "2014-07-08"
    },
    "2.4.7": {
      "name": "2.4.7",
      "date": "2014-07-08"
    },
    "2.3.17": {
      "name": "2.3.17",
      "date": "2014-07-07"
    },
    "2.5.0": {
      "name": "2.5.0",
      "date": "2014-05-31"
    },
    "2.4.6": {
      "name": "2.4.6",
      "date": "2014-05-31"
    },
    "2.3.16": {
      "name": "2.3.16",
      "date": "2014-05-31"
    },
    "2.4.5": {
      "name": "2.4.5",
      "date": "2014-05-22"
    },
    "2.3.15": {
      "name": "2.3.15",
      "date": "2014-05-22"
    },
    "2.3.14": {
      "name": "2.3.14",
      "date": "2014-05-22"
    },
    "2.4.4": {
      "name": "2.4.4",
      "date": "2014-04-27"
    },
    "2.3.13": {
      "name": "2.3.13",
      "date": "2014-04-27"
    },
    "2.4.3": {
      "name": "2.4.3",
      "date": "2014-04-04"
    },
    "2.3.12": {
      "name": "2.3.12",
      "date": "2014-04-03"
    },
    "2.3.11": {
      "name": "2.3.11",
      "date": "2014-02-27"
    },
    "2.4.2": {
      "name": "2.4.2",
      "date": "2014-02-12"
    },
    "2.3.10": {
      "name": "2.3.10",
      "date": "2014-02-12"
    },
    "2.4.1": {
      "name": "2.4.1",
      "date": "2014-01-05"
    },
    "2.3.9": {
      "name": "2.3.9",
      "date": "2014-01-05"
    },
    "2.3.8": {
      "name": "2.3.8",
      "date": "2013-12-16"
    },
    "2.4.0": {
      "name": "2.4.0",
      "date": "2013-12-03"
    },
    "2.2.11": {
      "name": "2.2.11",
      "date": "2013-12-02"
    },
    "2.3.7": {
      "name": "2.3.7",
      "date": "2013-11-14"
    },
    "2.2.10": {
      "name": "2.2.10",
      "date": "2013-11-13"
    },
    "2.3.6": {
      "name": "2.3.6",
      "date": "2013-10-10"
    },
    "2.2.9": {
      "name": "2.2.9",
      "date": "2013-10-10"
    },
    "2.1.13": {
      "name": "2.1.13",
      "date": "2013-10-10"
    },
    "2.0.25": {
      "name": "2.0.25",
      "date": "2013-10-10"
    },
    "2.3.5": {
      "name": "2.3.5",
      "date": "2013-09-27"
    },
    "2.2.8": {
      "name": "2.2.8",
      "date": "2013-09-26"
    },
    "2.2.7": {
      "name": "2.2.7",
      "date": "2013-09-26"
    },
    "2.3.4": {
      "name": "2.3.4",
      "date": "2013-08-27"
    },
    "2.2.6": {
      "name": "2.2.6",
      "date": "2013-08-26"
    },
    "2.3.3": {
      "name": "2.3.3",
      "date": "2013-08-07"
    },
    "2.2.5": {
      "name": "2.2.5",
      "date": "2013-08-07"
    },
    "2.1.12": {
      "name": "2.1.12",
      "date": "2013-08-07"
    },
    "2.0.24": {
      "name": "2.0.24",
      "date": "2013-08-07"
    },
    "2.3.2": {
      "name": "2.3.2",
      "date": "2013-07-17"
    },
    "2.2.4": {
      "name": "2.2.4",
      "date": "2013-07-15"
    },
    "2.2.3": {
      "name": "2.2.3",
      "date": "2013-06-19"
    },
    "2.3.1": {
      "name": "2.3.1",
      "date": "2013-06-11"
    },
    "2.3.0": {
      "name": "2.3.0",
      "date": "2013-06-03"
    },
    "2.2.2": {
      "name": "2.2.2",
      "date": "2013-06-02"
    },
    "2.1.11": {
      "name": "2.1.11",
      "date": "2013-06-02"
    },
    "2.1.10": {
      "name": "2.1.10",
      "date": "2013-05-06"
    },
    "2.2.1": {
      "name": "2.2.1",
      "date": "2013-04-06"
    },
    "2.1.9": {
      "name": "2.1.9",
      "date": "2013-03-26"
    },
    "2.0.23": {
      "name": "2.0.23",
      "date": "2013-03-20"
    },
    "2.2.0": {
      "name": "2.2.0",
      "date": "2013-03-01"
    },
    "2.1.8": {
      "name": "2.1.8",
      "date": "2013-02-23"
    },
    "2.1.7": {
      "name": "2.1.7",
      "date": "2013-01-17"
    },
    "2.0.22": {
      "name": "2.0.22",
      "date": "2013-01-17"
    },
    "2.1.6": {
      "name": "2.1.6",
      "date": "2012-12-21"
    },
    "2.0.21": {
      "name": "2.0.21",
      "date": "2012-12-21"
    },
    "2.1.5": {
      "name": "2.1.5",
      "date": "2012-12-20"
    },
    "2.0.20": {
      "name": "2.0.20",
      "date": "2012-12-20"
    },
    "2.1.4": {
      "name": "2.1.4",
      "date": "2012-11-29"
    },
    "2.0.19": {
      "name": "2.0.19",
      "date": "2012-11-29"
    },
    "2.1.3": {
      "name": "2.1.3",
      "date": "2012-10-30"
    },
    "2.0.18": {
      "name": "2.0.18",
      "date": "2012-10-25"
    },
    "2.1.2": {
      "name": "2.1.2",
      "date": "2012-09-20"
    },
    "2.1.1": {
      "name": "2.1.1",
      "date": "2012-09-11"
    },
    "2.1.0": {
      "name": "2.1.0",
      "date": "2012-09-06"
    },
    "2.0.17": {
      "name": "2.0.17",
      "date": "2012-08-28"
    },
    "2.0.16": {
      "name": "2.0.16",
      "date": "2012-07-11"
    },
    "2.0.15": {
      "name": "2.0.15",
      "date": "2012-05-30"
    },
    "2.0.14": {
      "name": "2.0.14",
      "date": "2012-05-17"
    },
    "2.0.13": {
      "name": "2.0.13",
      "date": "2012-04-30"
    },
    "2.0.12": {
      "name": "2.0.12",
      "date": "2012-03-19"
    },
    "2.0.11": {
      "name": "2.0.11",
      "date": "2012-02-24"
    },
    "2.0.10": {
      "name": "2.0.10",
      "date": "2012-02-06"
    },
    "2.0.9": {
      "name": "2.0.9",
      "date": "2012-01-06"
    },
    "2.0.8": {
      "name": "2.0.8",
      "date": "2011-12-26"
    },
    "2.0.7": {
      "name": "2.0.7",
      "date": "2011-12-08"
    },
    "2.0.6": {
      "name": "2.0.6",
      "date": "2011-11-16"
    },
    "2.0.5": {
      "name": "2.0.5",
      "date": "2011-11-02"
    },
    "2.0.4": {
      "name": "2.0.4",
      "date": "2011-10-04"
    },
    "2.0.3": {
      "name": "2.0.3",
      "date": "2011-09-25"
    },
    "2.0.2": {
      "name": "2.0.2",
      "date": "2011-09-25"
    },
    "2.0.1": {
      "name": "2.0.1",
      "date": "2011-08-26"
    },
    "2.0.0": {
      "name": "2.0.0",
      "date": "2011-07-28"
    }
  }
}